LICENSE
README.md
setup.py
localytics/__init__.py
localyticspy.egg-info/PKG-INFO
localyticspy.egg-info/SOURCES.txt
localyticspy.egg-info/dependency_links.txt
localyticspy.egg-info/requires.txt
localyticspy.egg-info/top_level.txt