Metadata-Version: 1.1
Name: localyticspy
Version: 0.1a1
Summary: Wrapper around localytics API
Home-page: https://github.com/nfdi/localyticspy
Author: Łukasz Żarnowiecki
Author-email: lukasz.z@nfdi.me
License: MIT
Download-URL: https://github.com/peterldowns/mypackage/tarball/0.1
Keywords: lib,library,localytics,wrapper,http
Platform: UNKNOWN
Classifier: Development Status :: 3 - Alpha
Classifier: Intended Audience :: Developers
Classifier: License :: OSI Approved :: MIT License
Classifier: Programming Language :: Python :: 3.5
